adafruit_dash_display.py
adafruit_circuitpython_dash_display-3.0.5.dist-info/licenses/LICENSE
adafruit_circuitpython_dash_display-3.0.5.dist-info/METADATA
adafruit_circuitpython_dash_display-3.0.5.dist-info/WHEEL
adafruit_circuitpython_dash_display-3.0.5.dist-info/top_level.txt
adafruit_circuitpython_dash_display-3.0.5.dist-info/RECORD
