Metadata-Version: 2.4
Name: adafruit-circuitpython-dash-display
Version: 3.0.5
Summary: CircuitPython library for creating Adafruit IO dashboards.
Author-email: Adafruit Industries <circuitpython@adafruit.com>
License: MIT
Project-URL: Homepage, https://github.com/adafruit/Adafruit_CircuitPython_Dash_Display
Keywords: adafruit,displays,iot,adafruitio,hardware,micropythoncircuitpython
Classifier: Intended Audience :: Developers
Classifier: Topic :: Software Development :: Libraries
Classifier: Topic :: Software Development :: Embedded Systems
Classifier: Topic :: System :: Hardware
Classifier: License :: OSI Approved :: MIT License
Classifier: Programming Language :: Python :: 3
License-File: LICENSE
Requires-Dist: Adafruit-Blinka
Requires-Dist: adafruit-circuitpython-display-text
Requires-Dist: adafruit-circuitpython-display-shapes
Requires-Dist: adafruit-circuitpython-adafruitio
Provides-Extra: optional
Dynamic: license-file
